LICENSE
MANIFEST.in
README.md
setup.py
khulnasoft_sdk.egg-info/PKG-INFO
khulnasoft_sdk.egg-info/SOURCES.txt
khulnasoft_sdk.egg-info/dependency_links.txt
khulnasoft_sdk.egg-info/requires.txt
khulnasoft_sdk.egg-info/top_level.txt
khulnasoftlib/__init__.py
khulnasoftlib/binding.py
khulnasoftlib/client.py
khulnasoftlib/data.py
khulnasoftlib/results.py
khulnasoftlib/utils.py
khulnasoftlib/modularinput/__init__.py
khulnasoftlib/modularinput/argument.py
khulnasoftlib/modularinput/event.py
khulnasoftlib/modularinput/event_writer.py
khulnasoftlib/modularinput/input_definition.py
khulnasoftlib/modularinput/scheme.py
khulnasoftlib/modularinput/script.py
khulnasoftlib/modularinput/utils.py
khulnasoftlib/modularinput/validation_definition.py
khulnasoftlib/searchcommands/__init__.py
khulnasoftlib/searchcommands/decorators.py
khulnasoftlib/searchcommands/environment.py
khulnasoftlib/searchcommands/eventing_command.py
khulnasoftlib/searchcommands/external_search_command.py
khulnasoftlib/searchcommands/generating_command.py
khulnasoftlib/searchcommands/internals.py
khulnasoftlib/searchcommands/reporting_command.py
khulnasoftlib/searchcommands/search_command.py
khulnasoftlib/searchcommands/streaming_command.py
khulnasoftlib/searchcommands/validators.py
tests/test_all.py
tests/test_app.py
tests/test_binding.py
tests/test_collection.py
tests/test_conf.py
tests/test_data.py
tests/test_event_type.py
tests/test_fired_alert.py
tests/test_index.py
tests/test_input.py
tests/test_job.py
tests/test_kvstore_batch.py
tests/test_kvstore_conf.py
tests/test_kvstore_data.py
tests/test_logger.py
tests/test_message.py
tests/test_modular_input.py
tests/test_modular_input_kinds.py
tests/test_results.py
tests/test_role.py
tests/test_saved_search.py
tests/test_service.py
tests/test_storage_passwords.py
tests/test_user.py
tests/test_utils.py
tests/testlib.py